LICENSE
MANIFEST.in
README.md
setup.cfg
setup.py
clusgeo/__init__.py
clusgeo/build.py
clusgeo/cluster.py
clusgeo/delaunay.py
clusgeo/utils.py
clusgeo.egg-info/PKG-INFO
clusgeo.egg-info/SOURCES.txt
clusgeo.egg-info/dependency_links.txt
clusgeo.egg-info/requires.txt
clusgeo.egg-info/top_level.txt
src/clusGeo3.c