Metadata-Version: 1.2
Name: clusgeo
Version: 4.1.0
Summary: CLUSter GEOmetry tool for surface chemistry.
Home-page: https://github.com/SINGROUP/SOAPLite
Author: Eiaki V. Morooka
Author-email: eiaki.morooka@aalto.fi
License: LGPLv3
Keywords: descriptor materials science machine learning soap local environment materials physics symmetry reduction adsorption sites
Platform: UNKNOWN
Classifier: Topic :: Scientific/Engineering :: Physics
Classifier: Operating System :: POSIX :: Linux
Classifier: Topic :: Scientific/Engineering :: Chemistry
Classifier: Topic :: Scientific/Engineering :: Artificial Intelligence
Classifier: License :: OSI Approved :: GNU Lesser General Public License v3 (LGPLv3)
Classifier: Development Status :: 4 - Beta
Classifier: Intended Audience :: Science/Research
Classifier: Intended Audience :: Religion
Classifier: Intended Audience :: Education
Classifier: Intended Audience :: Developers
Classifier: Programming Language :: Python
Classifier: Programming Language :: C
Requires-Python: >=2.2, <4
